brunno
