Metadata-Version: 1.1
Name: brunno
Version: 1.0.3
Summary: lib for math and phisyc
Home-page: https://github.com/perseu912/brunnopy
Author: Reinan Bezerra
Author-email: perseu912@gmail.com
License: MIT
Project-URL: Código fonte, https://github.com/perseu912
Project-URL: Download, https://github.com/perseu912/brunnopy/archive/master.zip
Keywords: fisica matematica funcoes especiais matematica computacional
Platform: UNKNOWN
Classifier: Development Status :: 5 - Production/Stable
Classifier: Intended Audience :: Developers
Classifier: License :: OSI Approved :: MIT License
Classifier: Natural Language :: Portuguese (Brazilian)
Classifier: Operating System :: OS Independent
Classifier: Topic :: Software Development :: Internationalization
Classifier: Topic :: Scientific/Engineering :: Physics
